api_random_protasevich/__init__.py
api_random_protasevich/core.py
api_random_protasevich-1.0.dist-info/LICENSE.txt
api_random_protasevich-1.0.dist-info/METADATA
api_random_protasevich-1.0.dist-info/WHEEL
api_random_protasevich-1.0.dist-info/top_level.txt
api_random_protasevich-1.0.dist-info/RECORD
